[{"image_id": 49932, "caption": "player in"}, {"image_id": 49933, "caption": "guy in"}, {"image_id": 49833, "caption": "woman in"}, {"image_id": 49834, "caption": "woman on left"}, {"image_id": 49747, "caption": "woman in"}, {"image_id": 49748, "caption": "woman"}, {"image_id": 49638, "caption": "guy on left"}, {"image_id": 49639, "caption": "guy on left"}, {"image_id": 49620, "caption": "man on left"}, {"image_id": 49621, "caption": "man in"}, {"image_id": 49622, "caption": "man in"}, {"image_id": 49606, "caption": "player"}, {"image_id": 49607, "caption": "man"}, {"image_id": 49600, "caption": "left person"}, {"image_id": 49601, "caption": "blue shirt"}, {"image_id": 49538, "caption": "woman in"}, {"image_id": 49539, "caption": "woman on left"}, {"image_id": 49457, "caption": "man on left"}, {"image_id": 49458, "caption": "man on right"}, {"image_id": 49373, "caption": "person in"}, {"image_id": 49374, "caption": "person in"}, {"image_id": 49375, "caption": "person in"}, {"image_id": 49315, "caption": "man in"}, {"image_id": 49316, "caption": "man in"}, {"image_id": 49312, "caption": "man on left"}, {"image_id": 49313, "caption": "man on left"}, {"image_id": 49199, "caption": "player in"}, {"image_id": 49200, "caption": "player in"}, {"image_id": 49201, "caption": "player in"}, {"image_id": 49014, "caption": "batter"}, {"image_id": 49015, "caption": "batter"}, {"image_id": 49016, "caption": "batter"}, {"image_id": 48983, "caption": "man"}, {"image_id": 48984, "caption": "woman"}, {"image_id": 48790, "caption": "man on left"}, {"image_id": 48791, "caption": "man in"}, {"image_id": 48745, "caption": "player on right"}, {"image_id": 48746, "caption": "player on right"}, {"image_id": 48705, "caption": "man on right"}, {"image_id": 48706, "caption": "man on left"}, {"image_id": 48707, "caption": "man on left"}, {"image_id": 48610, "caption": "girl on left"}, {"image_id": 48611, "caption": "girl in"}, {"image_id": 48571, "caption": "batter"}, {"image_id": 48572, "caption": "batter"}, {"image_id": 48476, "caption": "guy on right"}, {"image_id": 48477, "caption": "guy on right"}, {"image_id": 48478, "caption": "guy on right"}, {"image_id": 48473, "caption": "person in"}, {"image_id": 48474, "caption": "man in"}, {"image_id": 48475, "caption": "man in"}, {"image_id": 48374, "caption": "man in front"}, {"image_id": 48375, "caption": "man in"}, {"image_id": 48363, "caption": "woman in"}, {"image_id": 48364, "caption": "woman in"}, {"image_id": 48365, "caption": "woman in"}, {"image_id": 48322, "caption": "player on right"}, {"image_id": 48323, "caption": "player on right"}, {"image_id": 48304, "caption": "man in"}, {"image_id": 48305, "caption": "man in"}, {"image_id": 48201, "caption": "man on left"}, {"image_id": 48202, "caption": "man in"}, {"image_id": 48151, "caption": "batter"}, {"image_id": 48152, "caption": "batter"}, {"image_id": 48153, "caption": "batter"}, {"image_id": 48147, "caption": "woman"}, {"image_id": 48148, "caption": "woman"}, {"image_id": 48132, "caption": "left on left"}, {"image_id": 48133, "caption": "man in"}, {"image_id": 48134, "caption": "left pizza"}, {"image_id": 48135, "caption": "left pizza"}, {"image_id": 48006, "caption": "batter"}, {"image_id": 48007, "caption": "batter"}, {"image_id": 47999, "caption": "man in"}, {"image_id": 48000, "caption": "man on right"}, {"image_id": 48001, "caption": "man in"}, {"image_id": 47885, "caption": "player in"}, {"image_id": 47886, "caption": "player in"}, {"image_id": 47887, "caption": "player in"}, {"image_id": 47888, "caption": "player in"}, {"image_id": 47777, "caption": "person in"}, {"image_id": 47778, "caption": "man in"}, {"image_id": 47779, "caption": "man in"}, {"image_id": 47780, "caption": "man in"}, {"image_id": 47757, "caption": "woman on left"}, {"image_id": 47758, "caption": "woman on right"}, {"image_id": 47682, "caption": "woman in black"}, {"image_id": 47683, "caption": "woman in white"}, {"image_id": 47684, "caption": "woman in black"}, {"image_id": 47685, "caption": "woman in black"}, {"image_id": 47686, "caption": "woman in black"}, {"image_id": 47687, "caption": "woman in black"}, {"image_id": 47566, "caption": "car on right"}, {"image_id": 47567, "caption": "left on"}, {"image_id": 47568, "caption": "left on left"}, {"image_id": 47569, "caption": "white truck"}, {"image_id": 47519, "caption": "person in front"}, {"image_id": 47520, "caption": "person in"}, {"image_id": 47521, "caption": "person in front"}, {"image_id": 47522, "caption": "person in front"}, {"image_id": 47446, "caption": "man on right"}, {"image_id": 47447, "caption": "man on right"}, {"image_id": 47441, "caption": "man in"}, {"image_id": 47442, "caption": "man in"}, {"image_id": 47443, "caption": "man in"}, {"image_id": 47391, "caption": "man on right"}, {"image_id": 47392, "caption": "left on"}, {"image_id": 47393, "caption": "left on left left left"}, {"image_id": 47394, "caption": "man in"}, {"image_id": 47319, "caption": "girl in"}, {"image_id": 47164, "caption": "man in"}, {"image_id": 47165, "caption": "man in"}, {"image_id": 47092, "caption": "guy in"}, {"image_id": 47093, "caption": "guy in"}, {"image_id": 47094, "caption": "man in"}, {"image_id": 47077, "caption": "guy on right"}, {"image_id": 47014, "caption": "person on left"}, {"image_id": 47015, "caption": "man on right"}, {"image_id": 46949, "caption": "woman in"}, {"image_id": 46950, "caption": "woman in"}, {"image_id": 46951, "caption": "woman in"}, {"image_id": 46938, "caption": "woman in"}, {"image_id": 46939, "caption": "man in"}, {"image_id": 46940, "caption": "man on right"}, {"image_id": 46941, "caption": "man on right"}, {"image_id": 46880, "caption": "man on right"}, {"image_id": 46881, "caption": "man on right"}, {"image_id": 46838, "caption": "woman in"}, {"image_id": 46839, "caption": "woman in"}, {"image_id": 46834, "caption": "man in blue shirt"}, {"image_id": 46835, "caption": "man in blue shirt"}, {"image_id": 46836, "caption": "man in blue shirt"}, {"image_id": 46837, "caption": "man in blue shirt"}, {"image_id": 46823, "caption": "woman in"}, {"image_id": 46824, "caption": "man on left"}, {"image_id": 46678, "caption": "man in middle"}, {"image_id": 46679, "caption": "man in middle"}, {"image_id": 46680, "caption": "woman in front"}, {"image_id": 46681, "caption": "woman in front"}, {"image_id": 46682, "caption": "man in middle"}, {"image_id": 46683, "caption": "man in"}, {"image_id": 46672, "caption": "guy on right"}, {"image_id": 46673, "caption": "guy on right"}, {"image_id": 46581, "caption": "boy"}, {"image_id": 46582, "caption": "boy"}, {"image_id": 46555, "caption": "woman in"}, {"image_id": 46556, "caption": "woman in"}, {"image_id": 46451, "caption": "person in"}, {"image_id": 46452, "caption": "person on left"}, {"image_id": 46453, "caption": "man in"}, {"image_id": 46403, "caption": "person in"}, {"image_id": 46404, "caption": "person in"}, {"image_id": 46405, "caption": "person in"}, {"image_id": 46393, "caption": "woman in"}, {"image_id": 46394, "caption": "woman in"}, {"image_id": 46350, "caption": "woman in front"}, {"image_id": 46351, "caption": "woman in front"}, {"image_id": 46352, "caption": "woman in blue"}, {"image_id": 46353, "caption": "woman in front"}, {"image_id": 46321, "caption": "man in"}, {"image_id": 46322, "caption": "man in"}, {"image_id": 46285, "caption": "man in"}, {"image_id": 46286, "caption": "man on right"}, {"image_id": 46208, "caption": "woman in"}, {"image_id": 46209, "caption": "woman in"}, {"image_id": 46210, "caption": "woman in"}, {"image_id": 46211, "caption": "woman in"}, {"image_id": 46165, "caption": "batter"}, {"image_id": 46166, "caption": "batter"}, {"image_id": 46080, "caption": "batter"}, {"image_id": 46081, "caption": "batter"}, {"image_id": 45966, "caption": "woman in"}, {"image_id": 45967, "caption": "woman in"}, {"image_id": 45863, "caption": "guy in"}, {"image_id": 45864, "caption": "man in"}, {"image_id": 45865, "caption": "man in"}, {"image_id": 45837, "caption": "man in"}, {"image_id": 45838, "caption": "man in"}, {"image_id": 45839, "caption": "man in"}, {"image_id": 45840, "caption": "man in"}, {"image_id": 45841, "caption": "man in"}, {"image_id": 45675, "caption": "man in"}, {"image_id": 45676, "caption": "man in"}, {"image_id": 45677, "caption": "man in"}, {"image_id": 45600, "caption": "guy on right"}, {"image_id": 45601, "caption": "guy on right"}, {"image_id": 45434, "caption": "man in"}, {"image_id": 45435, "caption": "man in"}, {"image_id": 45436, "caption": "man in"}, {"image_id": 45407, "caption": "bike on right"}, {"image_id": 45367, "caption": "man in blue"}, {"image_id": 45368, "caption": "man in blue"}, {"image_id": 45369, "caption": "man in blue"}, {"image_id": 45358, "caption": "man in"}, {"image_id": 45359, "caption": "man in"}, {"image_id": 45340, "caption": "woman in"}, {"image_id": 45341, "caption": "woman in"}, {"image_id": 45342, "caption": "woman in"}, {"image_id": 45300, "caption": "batter"}, {"image_id": 45301, "caption": "batter"}, {"image_id": 45046, "caption": "man in front"}, {"image_id": 45047, "caption": "man in front"}, {"image_id": 45048, "caption": "man in front"}, {"image_id": 45049, "caption": "man in front"}, {"image_id": 45050, "caption": "man in front"}, {"image_id": 45051, "caption": "man in front"}, {"image_id": 45052, "caption": "man in front"}, {"image_id": 45019, "caption": "batter"}, {"image_id": 45020, "caption": "batter"}, {"image_id": 45021, "caption": "batter"}, {"image_id": 44766, "caption": "guy on left"}, {"image_id": 44740, "caption": "hand on right"}, {"image_id": 44741, "caption": "hand on right"}, {"image_id": 44732, "caption": "bike on right"}, {"image_id": 44733, "caption": "bike on right"}, {"image_id": 44714, "caption": "woman in"}, {"image_id": 44715, "caption": "woman in"}, {"image_id": 44699, "caption": "right on right"}, {"image_id": 44700, "caption": "left on"}, {"image_id": 44644, "caption": "man in"}, {"image_id": 44645, "caption": "man in"}, {"image_id": 44642, "caption": "person on right"}, {"image_id": 44643, "caption": "man in"}, {"image_id": 44633, "caption": "woman in"}, {"image_id": 44634, "caption": "woman in"}, {"image_id": 44635, "caption": "woman in"}, {"image_id": 44628, "caption": "woman in"}, {"image_id": 44629, "caption": "woman in"}, {"image_id": 44630, "caption": "woman in"}, {"image_id": 44582, "caption": "man in blue"}, {"image_id": 44583, "caption": "man in blue"}, {"image_id": 44584, "caption": "man in blue"}, {"image_id": 44553, "caption": "man in"}, {"image_id": 44554, "caption": "man in"}, {"image_id": 44517, "caption": "woman in"}, {"image_id": 44518, "caption": "girl in"}, {"image_id": 44519, "caption": "girl on left"}, {"image_id": 44448, "caption": "man in"}, {"image_id": 44449, "caption": "man on left"}, {"image_id": 44417, "caption": "player in"}, {"image_id": 44418, "caption": "player in"}, {"image_id": 44357, "caption": "man in blue"}, {"image_id": 44358, "caption": "man in blue"}, {"image_id": 44050, "caption": "man in"}, {"image_id": 44051, "caption": "man in"}, {"image_id": 44052, "caption": "man in"}, {"image_id": 44027, "caption": "player on right"}, {"image_id": 44028, "caption": "player on right"}, {"image_id": 43996, "caption": "red shirt"}, {"image_id": 43948, "caption": "man"}, {"image_id": 43949, "caption": "man"}, {"image_id": 43944, "caption": "man on left"}, {"image_id": 43945, "caption": "man in"}, {"image_id": 43647, "caption": "woman in"}, {"image_id": 43648, "caption": "woman in"}, {"image_id": 43535, "caption": "man in"}, {"image_id": 43536, "caption": "man in"}, {"image_id": 43537, "caption": "guy in"}, {"image_id": 43538, "caption": "man in"}, {"image_id": 43539, "caption": "guy in"}, {"image_id": 43379, "caption": "man in"}, {"image_id": 43380, "caption": "left guy"}, {"image_id": 43341, "caption": "white car"}, {"image_id": 43342, "caption": "man in"}, {"image_id": 43343, "caption": "guy on"}, {"image_id": 43344, "caption": "white car"}, {"image_id": 43315, "caption": "left on left left left left left left"}, {"image_id": 43316, "caption": "left on left left left left left left"}, {"image_id": 43317, "caption": "pizza on left"}, {"image_id": 43318, "caption": "left on left left left left left left left left"}, {"image_id": 43319, "caption": "pizza on right"}, {"image_id": 43320, "caption": "left on left left left left left left left left"}, {"image_id": 43313, "caption": "left on left left left left left"}, {"image_id": 43314, "caption": "left on left left left left left"}, {"image_id": 43311, "caption": "player on right"}, {"image_id": 43312, "caption": "player on right"}, {"image_id": 43298, "caption": "man in"}, {"image_id": 43299, "caption": "man in"}, {"image_id": 43300, "caption": "man in"}, {"image_id": 43288, "caption": "woman in"}, {"image_id": 43289, "caption": "man in blue shirt"}, {"image_id": 43290, "caption": "woman in"}, {"image_id": 43291, "caption": "man in blue shirt"}, {"image_id": 43292, "caption": "woman in"}, {"image_id": 43261, "caption": "baby"}, {"image_id": 43262, "caption": "baby"}, {"image_id": 43263, "caption": "baby"}, {"image_id": 43264, "caption": "baby"}, {"image_id": 43175, "caption": "motorcycle on right"}, {"image_id": 43176, "caption": "motorcycle on left"}, {"image_id": 43177, "caption": "motorcycle on right"}, {"image_id": 43178, "caption": "motorcycle on"}, {"image_id": 43179, "caption": "motorcycle on right"}, {"image_id": 43180, "caption": "motorcycle on"}, {"image_id": 43181, "caption": "motorcycle on right"}, {"image_id": 43162, "caption": "man on left"}, {"image_id": 43150, "caption": "guy on left"}, {"image_id": 43151, "caption": "man on right"}, {"image_id": 43152, "caption": "man on right"}, {"image_id": 43153, "caption": "man on right"}, {"image_id": 43088, "caption": "woman in"}, {"image_id": 43089, "caption": "woman in"}, {"image_id": 43003, "caption": "man in"}, {"image_id": 43004, "caption": "man in"}, {"image_id": 43005, "caption": "man in"}, {"image_id": 42896, "caption": "person in"}, {"image_id": 42897, "caption": "woman in"}, {"image_id": 42678, "caption": "guy"}, {"image_id": 42679, "caption": "guy"}, {"image_id": 42635, "caption": "man on right"}, {"image_id": 42636, "caption": "man on left"}, {"image_id": 42369, "caption": "man in"}, {"image_id": 42370, "caption": "man in"}, {"image_id": 42257, "caption": "man in"}, {"image_id": 42258, "caption": "man in"}, {"image_id": 42208, "caption": "person on left"}, {"image_id": 42209, "caption": "man in"}, {"image_id": 42189, "caption": "man in"}, {"image_id": 42190, "caption": "man on right"}, {"image_id": 42078, "caption": "person in"}, {"image_id": 42079, "caption": "man in"}, {"image_id": 42080, "caption": "person in"}, {"image_id": 42074, "caption": "left wine"}, {"image_id": 42075, "caption": "left on left left left left left left"}, {"image_id": 42076, "caption": "left on left left left left left left"}, {"image_id": 42077, "caption": "left on left left left left left"}, {"image_id": 41899, "caption": "man in"}, {"image_id": 41900, "caption": "man in"}, {"image_id": 41889, "caption": "man in"}, {"image_id": 41890, "caption": "woman in"}, {"image_id": 41812, "caption": "left guy"}, {"image_id": 41705, "caption": "elephant in"}, {"image_id": 41706, "caption": "left elephant"}, {"image_id": 41707, "caption": "elephant in"}, {"image_id": 41708, "caption": "elephant in"}, {"image_id": 41709, "caption": "middle in"}, {"image_id": 41679, "caption": "man in middle"}, {"image_id": 41680, "caption": "woman in middle"}, {"image_id": 41681, "caption": "man in middle"}, {"image_id": 41478, "caption": "man"}, {"image_id": 41479, "caption": "woman"}, {"image_id": 41457, "caption": "woman"}, {"image_id": 41458, "caption": "man"}, {"image_id": 41296, "caption": "man on right"}, {"image_id": 41297, "caption": "man on left"}, {"image_id": 41212, "caption": "man in"}, {"image_id": 41213, "caption": "man on right"}, {"image_id": 41214, "caption": "man in"}, {"image_id": 41215, "caption": "man in"}, {"image_id": 41067, "caption": "woman in"}, {"image_id": 41068, "caption": "woman in"}, {"image_id": 40878, "caption": "person on left"}, {"image_id": 40879, "caption": "man in"}, {"image_id": 40880, "caption": "man in"}, {"image_id": 40881, "caption": "man in"}, {"image_id": 40864, "caption": "man in"}, {"image_id": 40865, "caption": "man in"}, {"image_id": 40866, "caption": "woman in"}, {"image_id": 40856, "caption": "woman in"}, {"image_id": 40857, "caption": "woman in"}, {"image_id": 40808, "caption": "man in"}, {"image_id": 40809, "caption": "man in"}, {"image_id": 40725, "caption": "batter"}, {"image_id": 40726, "caption": "batter"}, {"image_id": 40695, "caption": "guy in"}, {"image_id": 40696, "caption": "guy on right"}, {"image_id": 40633, "caption": "batter"}, {"image_id": 40634, "caption": "batter"}, {"image_id": 40635, "caption": "batter"}, {"image_id": 40601, "caption": "man in front"}, {"image_id": 40602, "caption": "man in front"}, {"image_id": 40603, "caption": "man in front"}, {"image_id": 40567, "caption": "woman in"}, {"image_id": 40568, "caption": "woman in"}, {"image_id": 40496, "caption": "person on left"}, {"image_id": 40497, "caption": "person on right"}, {"image_id": 40498, "caption": "person on left"}, {"image_id": 40499, "caption": "person in"}, {"image_id": 40390, "caption": "player"}, {"image_id": 40391, "caption": "player"}, {"image_id": 40374, "caption": "woman in front"}, {"image_id": 40375, "caption": "woman in middle"}, {"image_id": 40376, "caption": "woman in middle"}, {"image_id": 40348, "caption": "woman in"}, {"image_id": 40349, "caption": "woman in"}, {"image_id": 40313, "caption": "woman in"}, {"image_id": 40314, "caption": "woman in"}, {"image_id": 40315, "caption": "woman in"}, {"image_id": 40316, "caption": "woman in"}, {"image_id": 40174, "caption": "man on right"}, {"image_id": 40175, "caption": "man on right"}, {"image_id": 40122, "caption": "player"}, {"image_id": 40123, "caption": "batter"}, {"image_id": 40011, "caption": "girl in"}, {"image_id": 40012, "caption": "man in"}, {"image_id": 40013, "caption": "girl in"}, {"image_id": 39929, "caption": "man in"}, {"image_id": 39930, "caption": "person in"}, {"image_id": 39931, "caption": "woman in"}, {"image_id": 39909, "caption": "man on right"}, {"image_id": 39910, "caption": "man on right"}, {"image_id": 39875, "caption": "girl in"}, {"image_id": 39876, "caption": "girl in"}, {"image_id": 39877, "caption": "girl in"}, {"image_id": 39839, "caption": "man in"}, {"image_id": 39755, "caption": "boy in"}, {"image_id": 39756, "caption": "boy in"}, {"image_id": 39644, "caption": "person on left"}, {"image_id": 39645, "caption": "man"}, {"image_id": 39646, "caption": "car"}, {"image_id": 39635, "caption": "man on right"}, {"image_id": 39636, "caption": "guy on left"}, {"image_id": 39596, "caption": "man in"}, {"image_id": 39597, "caption": "man in"}, {"image_id": 39598, "caption": "man in"}, {"image_id": 39599, "caption": "man in"}, {"image_id": 39600, "caption": "man in"}, {"image_id": 39593, "caption": "guy in"}, {"image_id": 39594, "caption": "guy in"}, {"image_id": 39595, "caption": "man in"}, {"image_id": 39550, "caption": "left laptop"}, {"image_id": 39551, "caption": "left monitor"}, {"image_id": 39552, "caption": "left monitor"}, {"image_id": 39553, "caption": "left monitor"}, {"image_id": 39554, "caption": "left laptop"}, {"image_id": 39555, "caption": "laptop"}, {"image_id": 39406, "caption": "man"}, {"image_id": 39407, "caption": "man on right"}, {"image_id": 39298, "caption": "woman in"}, {"image_id": 39299, "caption": "man in"}, {"image_id": 39180, "caption": "man in"}, {"image_id": 39181, "caption": "man in"}, {"image_id": 39182, "caption": "man in"}, {"image_id": 39183, "caption": "man in"}, {"image_id": 39139, "caption": "kid in"}, {"image_id": 39140, "caption": "kid in"}, {"image_id": 39141, "caption": "kid in"}, {"image_id": 39142, "caption": "kid in"}, {"image_id": 38938, "caption": "woman in"}, {"image_id": 38939, "caption": "woman in"}, {"image_id": 38856, "caption": "woman in"}, {"image_id": 38857, "caption": "person in"}, {"image_id": 38815, "caption": "man on left"}, {"image_id": 38816, "caption": "man in"}, {"image_id": 38742, "caption": "woman in"}, {"image_id": 38743, "caption": "woman in"}, {"image_id": 38744, "caption": "woman in"}, {"image_id": 38654, "caption": "man in"}, {"image_id": 38655, "caption": "person on left"}, {"image_id": 38656, "caption": "man in"}, {"image_id": 38650, "caption": "woman in"}, {"image_id": 38651, "caption": "woman in"}, {"image_id": 38587, "caption": "woman on left"}, {"image_id": 38588, "caption": "woman on left"}, {"image_id": 38589, "caption": "woman in"}, {"image_id": 38544, "caption": "girl on left"}, {"image_id": 38545, "caption": "woman in"}, {"image_id": 38546, "caption": "chair chair"}, {"image_id": 38547, "caption": "chair on left"}, {"image_id": 38504, "caption": "woman in"}, {"image_id": 38505, "caption": "woman in"}, {"image_id": 38506, "caption": "woman in"}, {"image_id": 38446, "caption": "man in"}, {"image_id": 38447, "caption": "man on right"}, {"image_id": 38448, "caption": "man in"}, {"image_id": 38449, "caption": "man in"}, {"image_id": 38417, "caption": "man on left"}, {"image_id": 38418, "caption": "man on right"}, {"image_id": 38419, "caption": "man on right"}, {"image_id": 38390, "caption": "man in"}, {"image_id": 38391, "caption": "man in"}, {"image_id": 38392, "caption": "man in"}, {"image_id": 38340, "caption": "man in"}, {"image_id": 38341, "caption": "guy in"}, {"image_id": 38274, "caption": "man in"}, {"image_id": 38275, "caption": "man in"}, {"image_id": 38276, "caption": "person in"}, {"image_id": 38227, "caption": "woman in"}, {"image_id": 38228, "caption": "woman in"}, {"image_id": 38214, "caption": "man in"}, {"image_id": 38215, "caption": "woman in"}, {"image_id": 38216, "caption": "man in"}, {"image_id": 37974, "caption": "woman"}, {"image_id": 37975, "caption": "woman"}, {"image_id": 37883, "caption": "man on right"}, {"image_id": 37884, "caption": "man on left"}, {"image_id": 37815, "caption": "man in"}, {"image_id": 37816, "caption": "man in"}, {"image_id": 37800, "caption": "boy"}, {"image_id": 37801, "caption": "boy"}, {"image_id": 37756, "caption": "girl in"}, {"image_id": 37757, "caption": "girl in"}, {"image_id": 37598, "caption": "guy in"}, {"image_id": 37599, "caption": "man in"}, {"image_id": 37600, "caption": "man in"}, {"image_id": 37478, "caption": "man in"}, {"image_id": 37479, "caption": "man in"}, {"image_id": 37472, "caption": "woman in"}, {"image_id": 37473, "caption": "left person"}, {"image_id": 37431, "caption": "man in"}, {"image_id": 37432, "caption": "man in"}, {"image_id": 37286, "caption": "man in"}, {"image_id": 37287, "caption": "man in"}, {"image_id": 37288, "caption": "man in"}, {"image_id": 37250, "caption": "guy in"}, {"image_id": 37251, "caption": "man in"}, {"image_id": 37125, "caption": "woman in"}, {"image_id": 37126, "caption": "man in"}, {"image_id": 37066, "caption": "man"}, {"image_id": 37067, "caption": "man"}, {"image_id": 37032, "caption": "batter"}, {"image_id": 37033, "caption": "batter"}, {"image_id": 36999, "caption": "guy on left"}, {"image_id": 37000, "caption": "man on right"}, {"image_id": 36993, "caption": "batter"}, {"image_id": 36994, "caption": "batter"}, {"image_id": 36928, "caption": "girl in"}, {"image_id": 36929, "caption": "girl in"}, {"image_id": 36930, "caption": "girl in"}, {"image_id": 36931, "caption": "girl in"}, {"image_id": 36911, "caption": "man on left"}, {"image_id": 36912, "caption": "man on right"}, {"image_id": 36913, "caption": "man on right"}, {"image_id": 36880, "caption": "player in"}, {"image_id": 36881, "caption": "player in"}, {"image_id": 36779, "caption": "man on left"}, {"image_id": 36780, "caption": "man in"}, {"image_id": 36691, "caption": "man in"}, {"image_id": 36692, "caption": "woman in"}, {"image_id": 36693, "caption": "man in"}, {"image_id": 36694, "caption": "woman in"}, {"image_id": 36545, "caption": "man in"}, {"image_id": 36546, "caption": "man in"}, {"image_id": 36426, "caption": "girl"}, {"image_id": 36427, "caption": "girl"}, {"image_id": 36160, "caption": "batter"}, {"image_id": 36161, "caption": "batter"}, {"image_id": 36162, "caption": "batter"}, {"image_id": 36051, "caption": "girl"}, {"image_id": 36052, "caption": "girl"}, {"image_id": 35975, "caption": "player on right"}, {"image_id": 35976, "caption": "player on left"}, {"image_id": 35970, "caption": "man in"}, {"image_id": 35965, "caption": "woman in"}, {"image_id": 35966, "caption": "woman in"}, {"image_id": 35848, "caption": "man in"}, {"image_id": 35849, "caption": "guy in"}, {"image_id": 35850, "caption": "man in"}, {"image_id": 35851, "caption": "man in"}, {"image_id": 35837, "caption": "man in"}, {"image_id": 35794, "caption": "left on left left left left left"}, {"image_id": 35795, "caption": "left on left"}, {"image_id": 35786, "caption": "woman"}, {"image_id": 35787, "caption": "girl"}, {"image_id": 35739, "caption": "girl on right"}, {"image_id": 35740, "caption": "woman in"}, {"image_id": 35710, "caption": "man in"}, {"image_id": 35711, "caption": "man in"}, {"image_id": 35654, "caption": "dog"}, {"image_id": 35655, "caption": "dog"}, {"image_id": 35656, "caption": "dog"}, {"image_id": 35657, "caption": "dog dog"}, {"image_id": 35615, "caption": "woman in blue"}, {"image_id": 35616, "caption": "woman in blue"}, {"image_id": 35407, "caption": "woman in"}, {"image_id": 35408, "caption": "woman in"}, {"image_id": 35409, "caption": "woman in"}, {"image_id": 35410, "caption": "woman in"}, {"image_id": 35411, "caption": "woman in"}, {"image_id": 35331, "caption": "man in"}, {"image_id": 35332, "caption": "man in"}, {"image_id": 35333, "caption": "man on left"}, {"image_id": 35319, "caption": "man in"}, {"image_id": 35320, "caption": "guy on left"}, {"image_id": 35305, "caption": "woman in"}, {"image_id": 35306, "caption": "woman"}, {"image_id": 35268, "caption": "woman"}, {"image_id": 35269, "caption": "woman in"}, {"image_id": 35206, "caption": "man in blue"}, {"image_id": 35207, "caption": "man in blue"}, {"image_id": 35208, "caption": "man in blue"}, {"image_id": 35209, "caption": "woman in blue"}, {"image_id": 35172, "caption": "left bike"}, {"image_id": 35100, "caption": "boy in"}, {"image_id": 35101, "caption": "boy in blue"}, {"image_id": 35066, "caption": "left on left left left left left left left left"}, {"image_id": 35067, "caption": "woman in"}, {"image_id": 34879, "caption": "batter"}, {"image_id": 34880, "caption": "batter"}, {"image_id": 34743, "caption": "man on left"}, {"image_id": 34744, "caption": "man in"}, {"image_id": 34745, "caption": "man on left"}, {"image_id": 34716, "caption": "man in"}, {"image_id": 34717, "caption": "man in"}, {"image_id": 34718, "caption": "man in"}, {"image_id": 34719, "caption": "man in"}, {"image_id": 34708, "caption": "woman in"}, {"image_id": 34709, "caption": "woman in"}, {"image_id": 34710, "caption": "woman in"}, {"image_id": 34711, "caption": "woman in"}, {"image_id": 34712, "caption": "woman in"}, {"image_id": 34713, "caption": "woman in"}, {"image_id": 34659, "caption": "woman in"}, {"image_id": 34660, "caption": "woman in"}, {"image_id": 34661, "caption": "girl in"}, {"image_id": 34655, "caption": "man on left"}, {"image_id": 34656, "caption": "man in"}, {"image_id": 34478, "caption": "man in"}, {"image_id": 34479, "caption": "man in"}, {"image_id": 34480, "caption": "woman in"}, {"image_id": 34481, "caption": "woman in"}, {"image_id": 34463, "caption": "man in"}, {"image_id": 34464, "caption": "man in"}, {"image_id": 34443, "caption": "woman in"}, {"image_id": 34444, "caption": "man in"}, {"image_id": 34445, "caption": "woman in"}, {"image_id": 34389, "caption": "man in"}, {"image_id": 34390, "caption": "man in"}, {"image_id": 34391, "caption": "man in"}, {"image_id": 34221, "caption": "man in"}, {"image_id": 34222, "caption": "man on left"}, {"image_id": 34093, "caption": "man in"}, {"image_id": 34094, "caption": "man in"}, {"image_id": 34095, "caption": "woman in"}, {"image_id": 33990, "caption": "girl"}, {"image_id": 33991, "caption": "girl"}, {"image_id": 33922, "caption": "man in"}, {"image_id": 33923, "caption": "woman in"}, {"image_id": 33924, "caption": "man in"}, {"image_id": 33925, "caption": "man in"}, {"image_id": 33926, "caption": "man in"}, {"image_id": 33819, "caption": "woman in"}, {"image_id": 33820, "caption": "woman in"}, {"image_id": 33821, "caption": "woman in"}, {"image_id": 33822, "caption": "woman in"}, {"image_id": 33696, "caption": "top right right right"}, {"image_id": 33697, "caption": "left left left left left left left left left left left left"}, {"image_id": 33698, "caption": "top left corner"}, {"image_id": 33633, "caption": "batter"}, {"image_id": 33634, "caption": "batter"}, {"image_id": 33631, "caption": "car"}, {"image_id": 33632, "caption": "white shirt"}, {"image_id": 33622, "caption": "girl in"}, {"image_id": 33623, "caption": "girl in"}, {"image_id": 33624, "caption": "woman in"}, {"image_id": 33625, "caption": "woman in"}, {"image_id": 33599, "caption": "man on left"}, {"image_id": 33600, "caption": "man"}, {"image_id": 33462, "caption": "batter"}, {"image_id": 33463, "caption": "batter"}, {"image_id": 33327, "caption": "the right"}, {"image_id": 33328, "caption": "the right"}, {"image_id": 33097, "caption": "man on right"}, {"image_id": 33098, "caption": "man on right"}, {"image_id": 33056, "caption": "man in"}, {"image_id": 33057, "caption": "man in"}, {"image_id": 33058, "caption": "man in"}, {"image_id": 33044, "caption": "man in"}, {"image_id": 33045, "caption": "man in"}, {"image_id": 33046, "caption": "man in"}, {"image_id": 32850, "caption": "man on right"}, {"image_id": 32851, "caption": "man on right"}, {"image_id": 32804, "caption": "man in"}, {"image_id": 32805, "caption": "man in"}, {"image_id": 32806, "caption": "man in"}, {"image_id": 32807, "caption": "man in"}, {"image_id": 32644, "caption": "left sheep"}, {"image_id": 32645, "caption": "left left left"}, {"image_id": 32646, "caption": "left sheep"}, {"image_id": 32647, "caption": "left left left left left"}, {"image_id": 32584, "caption": "batter"}, {"image_id": 32585, "caption": "batter"}, {"image_id": 32582, "caption": "woman in"}, {"image_id": 32583, "caption": "woman in"}, {"image_id": 32508, "caption": "batter"}, {"image_id": 32509, "caption": "batter"}, {"image_id": 32432, "caption": "left left left left left left left"}, {"image_id": 32433, "caption": "left on"}, {"image_id": 32298, "caption": "man"}, {"image_id": 32299, "caption": "boy in"}, {"image_id": 32234, "caption": "man on left"}, {"image_id": 32235, "caption": "man on right"}, {"image_id": 32217, "caption": "girl"}, {"image_id": 32218, "caption": "woman"}, {"image_id": 32164, "caption": "man on right"}, {"image_id": 31955, "caption": "woman in"}, {"image_id": 31956, "caption": "woman in"}, {"image_id": 31866, "caption": "man in"}, {"image_id": 31867, "caption": "man in"}, {"image_id": 31862, "caption": "woman"}, {"image_id": 31863, "caption": "woman"}, {"image_id": 31816, "caption": "man on left"}, {"image_id": 31817, "caption": "man on right"}, {"image_id": 31818, "caption": "man on right"}, {"image_id": 31799, "caption": "man on right"}, {"image_id": 31800, "caption": "man on right"}, {"image_id": 31762, "caption": "man in"}, {"image_id": 31763, "caption": "man in"}, {"image_id": 31764, "caption": "man in"}, {"image_id": 31765, "caption": "man in"}, {"image_id": 31597, "caption": "man in"}, {"image_id": 31598, "caption": "man in"}, {"image_id": 31599, "caption": "man in"}, {"image_id": 31600, "caption": "man in"}, {"image_id": 31601, "caption": "man in"}, {"image_id": 31572, "caption": "man on right"}, {"image_id": 31573, "caption": "man on left"}, {"image_id": 31552, "caption": "chair"}, {"image_id": 31553, "caption": "girl"}, {"image_id": 31554, "caption": "girl"}, {"image_id": 31555, "caption": "the"}, {"image_id": 31547, "caption": "girl in"}, {"image_id": 31548, "caption": "woman in"}, {"image_id": 31505, "caption": "batter"}, {"image_id": 31506, "caption": "batter"}, {"image_id": 31459, "caption": "man in"}, {"image_id": 31460, "caption": "man on left"}, {"image_id": 31461, "caption": "man in"}, {"image_id": 31462, "caption": "man in"}, {"image_id": 31356, "caption": "batter"}, {"image_id": 31357, "caption": "batter"}, {"image_id": 31358, "caption": "batter"}, {"image_id": 31206, "caption": "person in"}, {"image_id": 31207, "caption": "person in"}, {"image_id": 31201, "caption": "man in"}, {"image_id": 31202, "caption": "man in"}, {"image_id": 31203, "caption": "man in"}, {"image_id": 31198, "caption": "guy on right"}, {"image_id": 31199, "caption": "guy on"}, {"image_id": 30959, "caption": "girl"}, {"image_id": 30960, "caption": "baby"}, {"image_id": 30888, "caption": "right on right"}, {"image_id": 30889, "caption": "right hand"}, {"image_id": 30803, "caption": "man in"}, {"image_id": 30804, "caption": "guy on left"}, {"image_id": 30805, "caption": "man in"}, {"image_id": 30769, "caption": "man"}, {"image_id": 30770, "caption": "player"}, {"image_id": 30731, "caption": "man in"}, {"image_id": 30732, "caption": "woman in"}, {"image_id": 30676, "caption": "man on right"}, {"image_id": 30677, "caption": "man on left"}, {"image_id": 30637, "caption": "man on left"}, {"image_id": 30638, "caption": "left on"}, {"image_id": 30639, "caption": "left on"}, {"image_id": 30640, "caption": "man on right"}, {"image_id": 30556, "caption": "girl in"}, {"image_id": 30557, "caption": "woman in"}, {"image_id": 30558, "caption": "woman in"}, {"image_id": 30559, "caption": "woman in"}, {"image_id": 30560, "caption": "woman in"}, {"image_id": 30561, "caption": "woman in"}, {"image_id": 30562, "caption": "woman in"}, {"image_id": 30563, "caption": "woman in"}, {"image_id": 30525, "caption": "person on left"}, {"image_id": 30526, "caption": "man in"}, {"image_id": 30516, "caption": "man in"}, {"image_id": 30517, "caption": "man in"}, {"image_id": 30495, "caption": "woman in"}, {"image_id": 30496, "caption": "woman in"}, {"image_id": 30469, "caption": "man"}, {"image_id": 30470, "caption": "man"}, {"image_id": 30357, "caption": "woman in"}, {"image_id": 30358, "caption": "woman in"}, {"image_id": 30096, "caption": "man in"}, {"image_id": 30097, "caption": "man on left"}, {"image_id": 30098, "caption": "man in"}, {"image_id": 30099, "caption": "man in"}, {"image_id": 29956, "caption": "man in blue shirt"}, {"image_id": 29957, "caption": "man in blue shirt"}, {"image_id": 29908, "caption": "left person"}, {"image_id": 29909, "caption": "the right"}, {"image_id": 29910, "caption": "person in"}, {"image_id": 29882, "caption": "woman in"}, {"image_id": 29883, "caption": "woman in"}, {"image_id": 29811, "caption": "man in"}, {"image_id": 29812, "caption": "man on left"}, {"image_id": 29677, "caption": "person on left"}, {"image_id": 29678, "caption": "man in"}, {"image_id": 29637, "caption": "man in"}, {"image_id": 29638, "caption": "woman in"}, {"image_id": 29639, "caption": "woman in"}, {"image_id": 29640, "caption": "woman in"}, {"image_id": 29560, "caption": "player on right"}, {"image_id": 29561, "caption": "player on right"}, {"image_id": 29536, "caption": "man in"}, {"image_id": 29537, "caption": "man in"}, {"image_id": 29538, "caption": "man in"}, {"image_id": 29448, "caption": "batter"}, {"image_id": 29449, "caption": "batter"}, {"image_id": 29417, "caption": "woman"}, {"image_id": 29418, "caption": "girl"}, {"image_id": 29390, "caption": "motorcycle on"}, {"image_id": 29391, "caption": "bike on right"}, {"image_id": 29392, "caption": "motorcycle on"}, {"image_id": 29393, "caption": "bike on right"}, {"image_id": 29341, "caption": "player on"}, {"image_id": 29342, "caption": "player on right"}, {"image_id": 29236, "caption": "woman in"}, {"image_id": 29237, "caption": "left left left left left left left left left left left left"}, {"image_id": 29100, "caption": "man in"}, {"image_id": 29101, "caption": "man in"}, {"image_id": 29102, "caption": "man in"}, {"image_id": 29017, "caption": "man on right"}, {"image_id": 29018, "caption": "guy on"}, {"image_id": 29002, "caption": "man on right"}, {"image_id": 29003, "caption": "man on right"}, {"image_id": 28874, "caption": "girl in"}, {"image_id": 28875, "caption": "woman in"}, {"image_id": 28825, "caption": "man in"}, {"image_id": 28826, "caption": "man in"}, {"image_id": 28827, "caption": "man in"}, {"image_id": 28790, "caption": "woman in blue"}, {"image_id": 28791, "caption": "girl in"}, {"image_id": 28792, "caption": "woman in blue"}, {"image_id": 28788, "caption": "left person"}, {"image_id": 28789, "caption": "man on right"}, {"image_id": 28761, "caption": "man in"}, {"image_id": 28762, "caption": "man in"}, {"image_id": 28479, "caption": "the"}, {"image_id": 28480, "caption": "left dog"}, {"image_id": 28414, "caption": "batter"}, {"image_id": 28415, "caption": "batter"}, {"image_id": 28388, "caption": "man in"}, {"image_id": 28389, "caption": "man in"}, {"image_id": 28390, "caption": "man in"}, {"image_id": 28386, "caption": "person in"}, {"image_id": 28387, "caption": "person in"}, {"image_id": 28146, "caption": "white in"}, {"image_id": 28147, "caption": "left left left left"}, {"image_id": 28068, "caption": "man in"}, {"image_id": 28069, "caption": "guy in"}, {"image_id": 28070, "caption": "man in"}, {"image_id": 28059, "caption": "man in"}, {"image_id": 28060, "caption": "man in"}, {"image_id": 28061, "caption": "left left"}, {"image_id": 27957, "caption": "man on left"}, {"image_id": 27958, "caption": "man on right"}, {"image_id": 27946, "caption": "man in"}, {"image_id": 27947, "caption": "man in"}, {"image_id": 27948, "caption": "man in"}, {"image_id": 27949, "caption": "man in"}, {"image_id": 27950, "caption": "man in"}, {"image_id": 27775, "caption": "man in"}, {"image_id": 27776, "caption": "man in"}, {"image_id": 27728, "caption": "woman in"}, {"image_id": 27729, "caption": "woman in"}, {"image_id": 27717, "caption": "hand on"}, {"image_id": 27718, "caption": "hand on right"}, {"image_id": 27684, "caption": "man on left"}, {"image_id": 27685, "caption": "man on right"}, {"image_id": 27643, "caption": "man in"}, {"image_id": 27644, "caption": "man in"}, {"image_id": 27550, "caption": "man on left"}, {"image_id": 27551, "caption": "man in"}, {"image_id": 27489, "caption": "horse on right"}, {"image_id": 27490, "caption": "horse on"}, {"image_id": 27491, "caption": "horse on left"}, {"image_id": 27492, "caption": "horse on"}, {"image_id": 27493, "caption": "horse on right"}, {"image_id": 27447, "caption": "man in front"}, {"image_id": 27448, "caption": "man in front"}, {"image_id": 27366, "caption": "man in"}, {"image_id": 27367, "caption": "person in"}, {"image_id": 27368, "caption": "man in"}, {"image_id": 27369, "caption": "man in"}, {"image_id": 27370, "caption": "man in"}, {"image_id": 27212, "caption": "man in"}, {"image_id": 27213, "caption": "man in"}, {"image_id": 26977, "caption": "person in"}, {"image_id": 26978, "caption": "man in"}, {"image_id": 26877, "caption": "guy on right"}, {"image_id": 26878, "caption": "man on left"}, {"image_id": 26856, "caption": "person on left"}, {"image_id": 26857, "caption": "person in"}, {"image_id": 26858, "caption": "person in"}, {"image_id": 26749, "caption": "kid in"}, {"image_id": 26750, "caption": "kid in"}, {"image_id": 26751, "caption": "kid in middle"}, {"image_id": 26752, "caption": "kid in middle"}, {"image_id": 26744, "caption": "guy on right"}, {"image_id": 26745, "caption": "man on right"}, {"image_id": 26698, "caption": "woman in"}, {"image_id": 26699, "caption": "woman in"}, {"image_id": 26684, "caption": "player in"}, {"image_id": 26685, "caption": "player in"}, {"image_id": 26686, "caption": "player in"}, {"image_id": 26631, "caption": "woman in front"}, {"image_id": 26632, "caption": "woman in"}, {"image_id": 26633, "caption": "woman in"}, {"image_id": 26634, "caption": "woman in"}, {"image_id": 26628, "caption": "batter"}, {"image_id": 26629, "caption": "batter"}, {"image_id": 26630, "caption": "batter"}, {"image_id": 26571, "caption": "man in"}, {"image_id": 26572, "caption": "person in"}, {"image_id": 26509, "caption": "man on right"}, {"image_id": 26510, "caption": "man on right"}, {"image_id": 26498, "caption": "man in"}, {"image_id": 26499, "caption": "woman on left"}, {"image_id": 26263, "caption": "man in"}, {"image_id": 26264, "caption": "man in"}, {"image_id": 26265, "caption": "man in"}, {"image_id": 26266, "caption": "man in"}, {"image_id": 26267, "caption": "man in"}, {"image_id": 26086, "caption": "guy on left"}, {"image_id": 26087, "caption": "guy on right"}, {"image_id": 26088, "caption": "guy on right"}, {"image_id": 26089, "caption": "man in"}, {"image_id": 26042, "caption": "man on left"}, {"image_id": 26043, "caption": "man in"}, {"image_id": 25818, "caption": "batter"}, {"image_id": 25819, "caption": "batter"}, {"image_id": 25800, "caption": "person on left"}, {"image_id": 25801, "caption": "left on left left left left left left left left left"}, {"image_id": 25802, "caption": "left person"}, {"image_id": 25753, "caption": "man in"}, {"image_id": 25754, "caption": "man in"}, {"image_id": 25631, "caption": "woman in"}, {"image_id": 25632, "caption": "woman in"}, {"image_id": 25546, "caption": "batter"}, {"image_id": 25547, "caption": "batter"}, {"image_id": 25548, "caption": "player in"}, {"image_id": 25471, "caption": "player on right"}, {"image_id": 25472, "caption": "player on right"}, {"image_id": 25419, "caption": "batter"}, {"image_id": 25420, "caption": "batter"}, {"image_id": 25386, "caption": "left on left"}, {"image_id": 25387, "caption": "left on left"}, {"image_id": 25359, "caption": "man"}, {"image_id": 25360, "caption": "woman"}, {"image_id": 25334, "caption": "man on left"}, {"image_id": 25335, "caption": "man"}, {"image_id": 25077, "caption": "man in"}, {"image_id": 25078, "caption": "man in"}, {"image_id": 25002, "caption": "man in blue"}, {"image_id": 25003, "caption": "man in blue"}, {"image_id": 25004, "caption": "man in blue shirt"}, {"image_id": 24938, "caption": "man in"}, {"image_id": 24939, "caption": "man in"}, {"image_id": 24895, "caption": "woman in"}, {"image_id": 24896, "caption": "woman in"}, {"image_id": 24897, "caption": "woman in"}, {"image_id": 24891, "caption": "right dog"}, {"image_id": 24892, "caption": "right dog"}, {"image_id": 24893, "caption": "hand on right"}, {"image_id": 24894, "caption": "person on left"}, {"image_id": 24525, "caption": "man in"}, {"image_id": 24526, "caption": "man in"}, {"image_id": 24527, "caption": "man in"}, {"image_id": 24510, "caption": "man in"}, {"image_id": 24511, "caption": "man in"}, {"image_id": 24512, "caption": "woman on left"}, {"image_id": 24513, "caption": "man in"}, {"image_id": 24491, "caption": "woman in"}, {"image_id": 24492, "caption": "woman in"}, {"image_id": 24493, "caption": "woman in"}, {"image_id": 24454, "caption": "man on right"}, {"image_id": 24455, "caption": "man in"}, {"image_id": 24456, "caption": "guy on left"}, {"image_id": 24396, "caption": "man on left"}, {"image_id": 24397, "caption": "man on right"}, {"image_id": 24381, "caption": "man on right"}, {"image_id": 24382, "caption": "man on left"}, {"image_id": 24369, "caption": "woman in"}, {"image_id": 24370, "caption": "woman in"}, {"image_id": 24371, "caption": "woman in"}, {"image_id": 24320, "caption": "man on right"}, {"image_id": 24321, "caption": "guy on left"}, {"image_id": 24322, "caption": "guy on left"}, {"image_id": 24323, "caption": "man on right"}, {"image_id": 24297, "caption": "player on right"}, {"image_id": 24298, "caption": "player on right"}, {"image_id": 24265, "caption": "man in"}, {"image_id": 24266, "caption": "man in"}, {"image_id": 24267, "caption": "man in"}, {"image_id": 24237, "caption": "girl in"}, {"image_id": 24238, "caption": "girl in"}, {"image_id": 24063, "caption": "woman in"}, {"image_id": 24064, "caption": "woman in"}, {"image_id": 24061, "caption": "man in"}, {"image_id": 24062, "caption": "man in"}, {"image_id": 24058, "caption": "man in"}, {"image_id": 24059, "caption": "man in"}, {"image_id": 24060, "caption": "woman in"}, {"image_id": 24045, "caption": "woman in"}, {"image_id": 24046, "caption": "woman in"}, {"image_id": 23919, "caption": "man in"}, {"image_id": 23920, "caption": "man in"}, {"image_id": 23910, "caption": "left left left left left left left left left left"}, {"image_id": 23911, "caption": "girl"}, {"image_id": 23890, "caption": "man in"}, {"image_id": 23891, "caption": "man in"}, {"image_id": 23863, "caption": "man in blue"}, {"image_id": 23864, "caption": "man in blue"}, {"image_id": 23865, "caption": "guy in"}, {"image_id": 23866, "caption": "man in blue"}, {"image_id": 23857, "caption": "right right right right right right right right right right right right"}, {"image_id": 23652, "caption": "left on left"}, {"image_id": 23653, "caption": "woman in"}, {"image_id": 23654, "caption": "woman in"}, {"image_id": 23564, "caption": "man"}, {"image_id": 23565, "caption": "the"}, {"image_id": 23410, "caption": "man in"}, {"image_id": 23411, "caption": "man in"}, {"image_id": 23412, "caption": "man in"}, {"image_id": 23358, "caption": "batter"}, {"image_id": 23359, "caption": "batter"}, {"image_id": 23254, "caption": "man in"}, {"image_id": 23255, "caption": "man in"}, {"image_id": 23256, "caption": "man in"}, {"image_id": 23249, "caption": "man in"}, {"image_id": 23250, "caption": "man on left"}, {"image_id": 23251, "caption": "man in"}, {"image_id": 23235, "caption": "woman in middle"}, {"image_id": 23236, "caption": "man in"}, {"image_id": 23237, "caption": "woman in middle"}, {"image_id": 23192, "caption": "man on right"}, {"image_id": 23193, "caption": "man on left"}, {"image_id": 23194, "caption": "man on left"}, {"image_id": 23179, "caption": "woman in"}, {"image_id": 23180, "caption": "woman in"}, {"image_id": 23129, "caption": "man in"}, {"image_id": 23130, "caption": "man in"}, {"image_id": 23131, "caption": "man in"}, {"image_id": 23077, "caption": "person on right"}, {"image_id": 23078, "caption": "person on right"}, {"image_id": 23015, "caption": "man in"}, {"image_id": 23016, "caption": "woman in"}, {"image_id": 22862, "caption": "player on right"}, {"image_id": 22863, "caption": "player on right"}, {"image_id": 22796, "caption": "man in"}, {"image_id": 22797, "caption": "man in"}, {"image_id": 22798, "caption": "man in"}, {"image_id": 22715, "caption": "woman in"}, {"image_id": 22716, "caption": "woman in"}, {"image_id": 22717, "caption": "woman in"}, {"image_id": 22718, "caption": "woman in"}, {"image_id": 22659, "caption": "woman in"}, {"image_id": 22660, "caption": "woman in"}, {"image_id": 22504, "caption": "woman in"}, {"image_id": 22505, "caption": "woman in"}, {"image_id": 22475, "caption": "man on right"}, {"image_id": 22476, "caption": "man in"}, {"image_id": 22477, "caption": "man in"}, {"image_id": 22117, "caption": "batter"}, {"image_id": 22118, "caption": "batter"}, {"image_id": 22088, "caption": "man in"}, {"image_id": 22089, "caption": "man in"}, {"image_id": 22059, "caption": "girl in"}, {"image_id": 22060, "caption": "girl in"}, {"image_id": 22061, "caption": "girl in"}, {"image_id": 22062, "caption": "girl in"}, {"image_id": 22063, "caption": "girl in"}, {"image_id": 21798, "caption": "left on left left left left left"}, {"image_id": 21799, "caption": "left on left left left left"}, {"image_id": 21616, "caption": "top pizza"}, {"image_id": 21617, "caption": "top pizza"}, {"image_id": 21618, "caption": "top pizza"}, {"image_id": 21619, "caption": "pizza pizza"}, {"image_id": 21607, "caption": "woman in"}, {"image_id": 21608, "caption": "woman in"}, {"image_id": 21609, "caption": "woman in"}, {"image_id": 21580, "caption": "man on left"}, {"image_id": 21581, "caption": "man on right"}, {"image_id": 21525, "caption": "man in"}, {"image_id": 21444, "caption": "player on right"}, {"image_id": 21433, "caption": "man in"}, {"image_id": 21434, "caption": "man in"}, {"image_id": 21435, "caption": "man in"}, {"image_id": 21436, "caption": "man in"}, {"image_id": 21437, "caption": "man in"}, {"image_id": 21438, "caption": "man in"}, {"image_id": 21439, "caption": "man in"}, {"image_id": 21440, "caption": "man in"}, {"image_id": 21422, "caption": "man in"}, {"image_id": 21423, "caption": "man in"}, {"image_id": 21424, "caption": "man in"}, {"image_id": 21425, "caption": "man in"}, {"image_id": 21426, "caption": "guy in"}, {"image_id": 21410, "caption": "girl on right"}, {"image_id": 21411, "caption": "girl on right"}, {"image_id": 21302, "caption": "man in"}, {"image_id": 21303, "caption": "woman in"}, {"image_id": 21292, "caption": "man in"}, {"image_id": 21293, "caption": "man in"}, {"image_id": 21294, "caption": "man in"}, {"image_id": 21295, "caption": "man in"}, {"image_id": 21296, "caption": "man in"}, {"image_id": 21190, "caption": "woman in"}, {"image_id": 21191, "caption": "woman in"}, {"image_id": 21122, "caption": "woman in"}, {"image_id": 21123, "caption": "woman in"}, {"image_id": 21124, "caption": "woman in"}, {"image_id": 21125, "caption": "woman in"}, {"image_id": 21081, "caption": "blue in blue"}, {"image_id": 21082, "caption": "blue shirt"}, {"image_id": 21083, "caption": "blue shirt"}, {"image_id": 21084, "caption": "blue in blue"}, {"image_id": 21019, "caption": "girl in"}, {"image_id": 21020, "caption": "girl in"}, {"image_id": 20977, "caption": "left on left left left left left left left left left left"}, {"image_id": 20978, "caption": "left sandwich"}, {"image_id": 20954, "caption": "batter"}, {"image_id": 20946, "caption": "batter"}, {"image_id": 20947, "caption": "batter"}, {"image_id": 20948, "caption": "batter"}, {"image_id": 20938, "caption": "bottom right corner"}, {"image_id": 20939, "caption": "bottom left corner"}, {"image_id": 20940, "caption": "bottom left"}, {"image_id": 20941, "caption": "bottom left left"}, {"image_id": 20942, "caption": "man in front"}, {"image_id": 20943, "caption": "man in front"}, {"image_id": 20944, "caption": "man in middle"}, {"image_id": 20945, "caption": "bottom left"}, {"image_id": 20875, "caption": "man in"}, {"image_id": 20876, "caption": "woman in"}, {"image_id": 20877, "caption": "man in"}, {"image_id": 20791, "caption": "baby"}, {"image_id": 20792, "caption": "baby"}, {"image_id": 20755, "caption": "black shirt"}, {"image_id": 20756, "caption": "left on"}, {"image_id": 20757, "caption": "man in"}, {"image_id": 20663, "caption": "man in"}, {"image_id": 20664, "caption": "man in"}, {"image_id": 20665, "caption": "man in"}, {"image_id": 20666, "caption": "man in"}, {"image_id": 20667, "caption": "man in"}, {"image_id": 20668, "caption": "man in"}, {"image_id": 20649, "caption": "man in"}, {"image_id": 20650, "caption": "man in"}, {"image_id": 20602, "caption": "woman in"}, {"image_id": 20603, "caption": "woman in"}, {"image_id": 20512, "caption": "man in"}, {"image_id": 20513, "caption": "woman in"}, {"image_id": 20514, "caption": "woman in"}, {"image_id": 20505, "caption": "woman in"}, {"image_id": 20506, "caption": "woman in"}, {"image_id": 20479, "caption": "guy on right"}, {"image_id": 20480, "caption": "man in"}, {"image_id": 20469, "caption": "man in"}, {"image_id": 20470, "caption": "man in"}, {"image_id": 20471, "caption": "man in"}, {"image_id": 20454, "caption": "hand on left"}, {"image_id": 20455, "caption": "hand"}, {"image_id": 20420, "caption": "man on left"}, {"image_id": 20421, "caption": "man on right"}, {"image_id": 20389, "caption": "person on right"}, {"image_id": 20390, "caption": "person on"}, {"image_id": 20311, "caption": "pizza pizza"}, {"image_id": 20312, "caption": "pizza pizza"}, {"image_id": 20313, "caption": "pizza pizza"}, {"image_id": 20314, "caption": "pizza pizza"}, {"image_id": 20315, "caption": "pizza pizza"}, {"image_id": 20268, "caption": "boy"}, {"image_id": 20269, "caption": "boy"}, {"image_id": 20246, "caption": "man"}, {"image_id": 20247, "caption": "left guy"}, {"image_id": 20099, "caption": "guy on right"}, {"image_id": 20100, "caption": "guy in"}, {"image_id": 20101, "caption": "guy on left"}, {"image_id": 20102, "caption": "guy on right"}, {"image_id": 20103, "caption": "guy in"}, {"image_id": 20041, "caption": "woman in"}, {"image_id": 20042, "caption": "woman in"}, {"image_id": 19941, "caption": "man in"}, {"image_id": 19942, "caption": "man in middle"}, {"image_id": 19901, "caption": "man in"}, {"image_id": 19902, "caption": "man in"}, {"image_id": 19903, "caption": "man in"}, {"image_id": 19904, "caption": "man in"}, {"image_id": 19843, "caption": "woman in"}, {"image_id": 19844, "caption": "left on left left left left left left left left"}, {"image_id": 19743, "caption": "person in"}, {"image_id": 19744, "caption": "left on left"}, {"image_id": 19745, "caption": "table"}, {"image_id": 19746, "caption": "person in"}, {"image_id": 19732, "caption": "man"}, {"image_id": 19733, "caption": "man"}, {"image_id": 19686, "caption": "woman in"}, {"image_id": 19687, "caption": "woman in"}, {"image_id": 19688, "caption": "woman in"}, {"image_id": 19684, "caption": "left on"}, {"image_id": 19685, "caption": "dog"}, {"image_id": 19634, "caption": "left"}, {"image_id": 19635, "caption": "baby"}, {"image_id": 19543, "caption": "man in"}, {"image_id": 19516, "caption": "man in"}, {"image_id": 19517, "caption": "man in"}, {"image_id": 19512, "caption": "batter"}, {"image_id": 19513, "caption": "batter"}, {"image_id": 19514, "caption": "batter"}, {"image_id": 19515, "caption": "batter"}, {"image_id": 19509, "caption": "man in"}, {"image_id": 19510, "caption": "man in"}, {"image_id": 19511, "caption": "man in"}, {"image_id": 19469, "caption": "girl on left"}, {"image_id": 19470, "caption": "left pizza"}, {"image_id": 19471, "caption": "left on left left left left left left left left"}, {"image_id": 19448, "caption": "girl in"}, {"image_id": 19449, "caption": "woman in"}, {"image_id": 19450, "caption": "woman in"}, {"image_id": 19451, "caption": "woman in"}, {"image_id": 19433, "caption": "person on left"}, {"image_id": 19434, "caption": "person on right"}, {"image_id": 19428, "caption": "man in"}, {"image_id": 19429, "caption": "man on right"}, {"image_id": 19430, "caption": "man on right"}, {"image_id": 19348, "caption": "man"}, {"image_id": 19349, "caption": "left guy"}, {"image_id": 19325, "caption": "kid"}, {"image_id": 19326, "caption": "boy"}, {"image_id": 19327, "caption": "kid"}, {"image_id": 19279, "caption": "black shirt"}, {"image_id": 19280, "caption": "black shirt"}, {"image_id": 19132, "caption": "guy in front"}, {"image_id": 19133, "caption": "man in front"}, {"image_id": 19134, "caption": "man in front"}, {"image_id": 19062, "caption": "guy in"}, {"image_id": 19063, "caption": "man in"}, {"image_id": 19064, "caption": "man in"}, {"image_id": 19040, "caption": "guy in"}, {"image_id": 19008, "caption": "man in"}, {"image_id": 18931, "caption": "man in"}, {"image_id": 18932, "caption": "guy in"}, {"image_id": 18933, "caption": "man in"}, {"image_id": 18934, "caption": "man in"}, {"image_id": 18935, "caption": "man in"}, {"image_id": 18936, "caption": "guy in"}, {"image_id": 18937, "caption": "man in"}, {"image_id": 18938, "caption": "man in"}, {"image_id": 18912, "caption": "guy on right"}, {"image_id": 18913, "caption": "guy on right"}, {"image_id": 18914, "caption": "guy on right"}, {"image_id": 18888, "caption": "guy in"}, {"image_id": 18889, "caption": "man in"}, {"image_id": 18846, "caption": "person on left"}, {"image_id": 18847, "caption": "man on right"}, {"image_id": 18806, "caption": "left person"}, {"image_id": 18804, "caption": "guy on right"}, {"image_id": 18805, "caption": "guy on right"}, {"image_id": 18798, "caption": "woman in"}, {"image_id": 18799, "caption": "woman in"}, {"image_id": 18800, "caption": "man in"}, {"image_id": 18738, "caption": "woman in"}, {"image_id": 18739, "caption": "woman in"}, {"image_id": 18740, "caption": "woman in"}, {"image_id": 18701, "caption": "man"}, {"image_id": 18702, "caption": "player"}, {"image_id": 18703, "caption": "player"}, {"image_id": 18704, "caption": "player"}, {"image_id": 18584, "caption": "man in"}, {"image_id": 18585, "caption": "man in"}, {"image_id": 18586, "caption": "man in"}, {"image_id": 18488, "caption": "guy in"}, {"image_id": 18489, "caption": "man in"}, {"image_id": 18490, "caption": "man in"}, {"image_id": 18448, "caption": "woman in"}, {"image_id": 18449, "caption": "woman in"}, {"image_id": 18362, "caption": "umbrella"}, {"image_id": 18363, "caption": "man in"}, {"image_id": 18364, "caption": "person in"}, {"image_id": 18325, "caption": "man in"}, {"image_id": 18326, "caption": "man on left"}, {"image_id": 18297, "caption": "man"}, {"image_id": 18298, "caption": "man"}, {"image_id": 18274, "caption": "man in"}, {"image_id": 18275, "caption": "man in"}, {"image_id": 18276, "caption": "man in"}, {"image_id": 18277, "caption": "man in"}, {"image_id": 18278, "caption": "man in"}, {"image_id": 18167, "caption": "left couch"}, {"image_id": 18168, "caption": "left on"}, {"image_id": 18169, "caption": "left couch"}, {"image_id": 18170, "caption": "left on left left left left left left"}, {"image_id": 18163, "caption": "guy on left"}, {"image_id": 18164, "caption": "man"}, {"image_id": 18162, "caption": "woman in"}, {"image_id": 18127, "caption": "woman in"}, {"image_id": 18128, "caption": "woman in"}, {"image_id": 18064, "caption": "man in"}, {"image_id": 18065, "caption": "man in"}, {"image_id": 18066, "caption": "man in"}, {"image_id": 18067, "caption": "man in"}, {"image_id": 17986, "caption": "man on right"}, {"image_id": 17987, "caption": "man on right"}, {"image_id": 17974, "caption": "batter"}, {"image_id": 17975, "caption": "batter"}, {"image_id": 17976, "caption": "batter"}, {"image_id": 17977, "caption": "batter"}, {"image_id": 17906, "caption": "woman in"}, {"image_id": 17907, "caption": "woman in"}, {"image_id": 17731, "caption": "man on left"}, {"image_id": 17732, "caption": "man in"}, {"image_id": 17715, "caption": "woman in"}, {"image_id": 17716, "caption": "woman in blue"}, {"image_id": 17717, "caption": "woman in blue"}, {"image_id": 17643, "caption": "woman in"}, {"image_id": 17644, "caption": "woman in"}, {"image_id": 17629, "caption": "girl"}, {"image_id": 17630, "caption": "left left left left left left left left left left"}, {"image_id": 17622, "caption": "batter"}, {"image_id": 17623, "caption": "batter"}, {"image_id": 17579, "caption": "man in"}, {"image_id": 17580, "caption": "man on left"}, {"image_id": 17545, "caption": "man in"}, {"image_id": 17546, "caption": "kid in"}, {"image_id": 17523, "caption": "man on left"}, {"image_id": 17524, "caption": "man on left"}, {"image_id": 17497, "caption": "black bag"}, {"image_id": 17498, "caption": "black in"}, {"image_id": 17488, "caption": "person in"}, {"image_id": 17489, "caption": "man in"}, {"image_id": 17322, "caption": "batter"}, {"image_id": 17323, "caption": "batter"}, {"image_id": 17324, "caption": "batter"}, {"image_id": 17138, "caption": "man in"}, {"image_id": 17139, "caption": "man in"}, {"image_id": 17039, "caption": "person in"}, {"image_id": 17040, "caption": "person in"}, {"image_id": 16896, "caption": "the"}, {"image_id": 16897, "caption": "the"}, {"image_id": 16898, "caption": "hand"}, {"image_id": 16892, "caption": "man on right"}, {"image_id": 16804, "caption": "woman in"}, {"image_id": 16805, "caption": "woman in"}, {"image_id": 16786, "caption": "man on right"}, {"image_id": 16787, "caption": "man on right"}, {"image_id": 16788, "caption": "man on right"}, {"image_id": 16738, "caption": "man in"}, {"image_id": 16739, "caption": "man in"}, {"image_id": 16740, "caption": "man in"}, {"image_id": 16741, "caption": "man in"}, {"image_id": 16732, "caption": "man in"}, {"image_id": 16636, "caption": "left horse"}, {"image_id": 16566, "caption": "man in"}, {"image_id": 16567, "caption": "person in front"}, {"image_id": 16568, "caption": "person in front"}, {"image_id": 16569, "caption": "person in front"}, {"image_id": 16543, "caption": "person in"}, {"image_id": 16544, "caption": "man in"}, {"image_id": 16545, "caption": "person in"}, {"image_id": 16425, "caption": "player on right"}, {"image_id": 16426, "caption": "player on right"}, {"image_id": 16200, "caption": "man on left"}, {"image_id": 16201, "caption": "man in"}, {"image_id": 16126, "caption": "woman in middle"}, {"image_id": 16127, "caption": "woman in"}, {"image_id": 16128, "caption": "woman in"}, {"image_id": 16129, "caption": "woman in"}, {"image_id": 16130, "caption": "woman in"}, {"image_id": 16131, "caption": "woman in"}, {"image_id": 16077, "caption": "man on right"}, {"image_id": 16078, "caption": "man on right"}, {"image_id": 16068, "caption": "player on right"}, {"image_id": 16069, "caption": "player in"}, {"image_id": 15986, "caption": "woman in"}, {"image_id": 15987, "caption": "man in"}, {"image_id": 15825, "caption": "man on left"}, {"image_id": 15826, "caption": "man on left"}, {"image_id": 15754, "caption": "left on left left left"}, {"image_id": 15755, "caption": "left on left left"}, {"image_id": 15699, "caption": "woman in"}, {"image_id": 15563, "caption": "woman in"}, {"image_id": 15564, "caption": "woman in"}, {"image_id": 15555, "caption": "man in"}, {"image_id": 15556, "caption": "man in"}, {"image_id": 15432, "caption": "boy in"}, {"image_id": 15433, "caption": "person in"}, {"image_id": 15394, "caption": "the"}, {"image_id": 15366, "caption": "woman in"}, {"image_id": 15367, "caption": "woman in"}, {"image_id": 15368, "caption": "woman in"}, {"image_id": 15369, "caption": "woman in"}, {"image_id": 15370, "caption": "woman in"}, {"image_id": 15348, "caption": "left on"}, {"image_id": 15349, "caption": "left horse"}, {"image_id": 15342, "caption": "man in"}, {"image_id": 15343, "caption": "man on left"}, {"image_id": 15253, "caption": "man on right"}, {"image_id": 15254, "caption": "man on left"}, {"image_id": 15255, "caption": "man on left"}, {"image_id": 15092, "caption": "man on left"}, {"image_id": 15093, "caption": "man on right"}, {"image_id": 15094, "caption": "man on right"}, {"image_id": 15085, "caption": "man in"}, {"image_id": 15086, "caption": "man in"}, {"image_id": 15087, "caption": "man in"}, {"image_id": 15088, "caption": "man in"}, {"image_id": 15089, "caption": "man in"}, {"image_id": 14981, "caption": "man in"}, {"image_id": 14982, "caption": "man in"}, {"image_id": 14968, "caption": "left on left left left left left"}, {"image_id": 14969, "caption": "left guy"}, {"image_id": 14940, "caption": "player in"}, {"image_id": 14941, "caption": "player in"}, {"image_id": 14883, "caption": "man in"}, {"image_id": 14884, "caption": "guy on left"}, {"image_id": 14869, "caption": "man in"}, {"image_id": 14870, "caption": "man in"}, {"image_id": 14855, "caption": "person in"}, {"image_id": 14856, "caption": "person in"}, {"image_id": 14857, "caption": "person in"}, {"image_id": 14755, "caption": "batter"}, {"image_id": 14756, "caption": "batter"}, {"image_id": 14757, "caption": "batter"}, {"image_id": 14694, "caption": "guy on"}, {"image_id": 14695, "caption": "guy on"}, {"image_id": 14601, "caption": "man in"}, {"image_id": 14602, "caption": "man in"}, {"image_id": 14603, "caption": "man in"}, {"image_id": 14521, "caption": "woman in"}, {"image_id": 14522, "caption": "man in"}, {"image_id": 14523, "caption": "man in"}, {"image_id": 14524, "caption": "man in"}, {"image_id": 14519, "caption": "man in"}, {"image_id": 14520, "caption": "woman in"}, {"image_id": 14482, "caption": "girl"}, {"image_id": 14483, "caption": "woman"}, {"image_id": 14377, "caption": "girl in"}, {"image_id": 14378, "caption": "woman in"}, {"image_id": 14379, "caption": "woman in"}, {"image_id": 14380, "caption": "woman in"}, {"image_id": 14352, "caption": "man in"}, {"image_id": 14353, "caption": "yellow shirt"}, {"image_id": 14316, "caption": "man"}, {"image_id": 14317, "caption": "woman"}, {"image_id": 14274, "caption": "batter"}, {"image_id": 14275, "caption": "batter"}, {"image_id": 14276, "caption": "batter"}, {"image_id": 14277, "caption": "batter"}, {"image_id": 14270, "caption": "bike bike"}, {"image_id": 14271, "caption": "bike bike"}, {"image_id": 14272, "caption": "bike bike"}, {"image_id": 14273, "caption": "bike bike"}, {"image_id": 14201, "caption": "the"}, {"image_id": 14202, "caption": "woman"}, {"image_id": 14203, "caption": "chair"}, {"image_id": 14204, "caption": "chair"}, {"image_id": 14102, "caption": "man in"}, {"image_id": 14103, "caption": "man in"}, {"image_id": 14104, "caption": "man in"}, {"image_id": 14105, "caption": "man in"}, {"image_id": 14106, "caption": "man in"}, {"image_id": 14038, "caption": "blue chair"}, {"image_id": 14039, "caption": "left chair"}, {"image_id": 14040, "caption": "blue chair"}, {"image_id": 14041, "caption": "chair on the"}, {"image_id": 14042, "caption": "blue chair"}, {"image_id": 14024, "caption": "pizza"}, {"image_id": 14025, "caption": "pizza"}, {"image_id": 14026, "caption": "pizza pizza"}, {"image_id": 14027, "caption": "pizza on left"}, {"image_id": 13894, "caption": "man in"}, {"image_id": 13895, "caption": "man on right"}, {"image_id": 13869, "caption": "girl in"}, {"image_id": 13870, "caption": "woman in"}, {"image_id": 13793, "caption": "woman in"}, {"image_id": 13794, "caption": "man in"}, {"image_id": 13625, "caption": "girl in"}, {"image_id": 13626, "caption": "girl in"}, {"image_id": 13627, "caption": "girl in"}, {"image_id": 13439, "caption": "girl on left"}, {"image_id": 13440, "caption": "girl on left"}, {"image_id": 13441, "caption": "woman in"}, {"image_id": 13442, "caption": "girl in"}, {"image_id": 13410, "caption": "woman in"}, {"image_id": 13411, "caption": "woman in"}, {"image_id": 13412, "caption": "woman in"}, {"image_id": 13386, "caption": "man on left"}, {"image_id": 13387, "caption": "man in"}, {"image_id": 13382, "caption": "player on right"}, {"image_id": 13383, "caption": "player on right"}, {"image_id": 13373, "caption": "person in"}, {"image_id": 13374, "caption": "person in"}, {"image_id": 13236, "caption": "bowl on left"}, {"image_id": 13237, "caption": "bowl on left"}, {"image_id": 13238, "caption": "bowl on left"}, {"image_id": 13239, "caption": "bowl on left"}, {"image_id": 13209, "caption": "woman in"}, {"image_id": 13210, "caption": "woman in"}, {"image_id": 13087, "caption": "man"}, {"image_id": 13088, "caption": "man on left"}, {"image_id": 13055, "caption": "man in"}, {"image_id": 13056, "caption": "man in"}, {"image_id": 13057, "caption": "man on left"}, {"image_id": 12963, "caption": "person in"}, {"image_id": 12964, "caption": "person in"}, {"image_id": 12758, "caption": "man in"}, {"image_id": 12759, "caption": "man on left"}, {"image_id": 12719, "caption": "woman in"}, {"image_id": 12720, "caption": "woman in"}, {"image_id": 12721, "caption": "woman in"}, {"image_id": 12665, "caption": "person on left"}, {"image_id": 12666, "caption": "man"}, {"image_id": 12357, "caption": "woman on left"}, {"image_id": 12358, "caption": "woman in"}, {"image_id": 12261, "caption": "person in"}, {"image_id": 12262, "caption": "front in"}, {"image_id": 12263, "caption": "right in"}, {"image_id": 12025, "caption": "man in"}, {"image_id": 12026, "caption": "man in"}, {"image_id": 12027, "caption": "man in"}, {"image_id": 12028, "caption": "man in"}, {"image_id": 12029, "caption": "man in"}, {"image_id": 12030, "caption": "man in"}, {"image_id": 12023, "caption": "the right"}, {"image_id": 12024, "caption": "left on left left left"}, {"image_id": 12001, "caption": "batter"}, {"image_id": 12002, "caption": "batter"}, {"image_id": 11894, "caption": "player in"}, {"image_id": 11895, "caption": "man in"}, {"image_id": 11769, "caption": "the"}, {"image_id": 11770, "caption": "the"}, {"image_id": 11757, "caption": "man on right"}, {"image_id": 11758, "caption": "guy on left"}, {"image_id": 11752, "caption": "woman in"}, {"image_id": 11753, "caption": "woman in"}, {"image_id": 11676, "caption": "man on right"}, {"image_id": 11677, "caption": "man on right"}, {"image_id": 11637, "caption": "man in"}, {"image_id": 11638, "caption": "woman in"}, {"image_id": 11639, "caption": "woman in"}, {"image_id": 11541, "caption": "woman in"}, {"image_id": 11409, "caption": "batter"}, {"image_id": 11410, "caption": "batter"}, {"image_id": 11411, "caption": "batter"}, {"image_id": 11372, "caption": "left on left"}, {"image_id": 11373, "caption": "the right"}, {"image_id": 11224, "caption": "guy on right"}, {"image_id": 11225, "caption": "guy on right"}, {"image_id": 11203, "caption": "man in"}, {"image_id": 11204, "caption": "person in"}, {"image_id": 11205, "caption": "man in"}, {"image_id": 11159, "caption": "woman in front"}, {"image_id": 11160, "caption": "woman in front"}, {"image_id": 11161, "caption": "woman in"}, {"image_id": 11101, "caption": "player in"}, {"image_id": 11102, "caption": "player in"}, {"image_id": 11103, "caption": "player in"}, {"image_id": 11104, "caption": "player in"}, {"image_id": 11032, "caption": "person on right"}, {"image_id": 11033, "caption": "person on left"}, {"image_id": 11025, "caption": "woman in"}, {"image_id": 11026, "caption": "woman in"}, {"image_id": 11027, "caption": "woman in"}, {"image_id": 11019, "caption": "left dog"}, {"image_id": 11020, "caption": "left on left"}, {"image_id": 11021, "caption": "left on left left left"}, {"image_id": 11022, "caption": "left on"}, {"image_id": 11023, "caption": "left on left left left"}, {"image_id": 11024, "caption": "left dog"}, {"image_id": 10995, "caption": "girl in"}, {"image_id": 10996, "caption": "woman in"}, {"image_id": 10895, "caption": "woman in"}, {"image_id": 10896, "caption": "woman in"}, {"image_id": 10879, "caption": "woman"}, {"image_id": 10749, "caption": "man in"}, {"image_id": 10750, "caption": "man in"}, {"image_id": 10629, "caption": "man on left"}, {"image_id": 10630, "caption": "man on right"}, {"image_id": 10554, "caption": "man in"}, {"image_id": 10555, "caption": "woman in"}, {"image_id": 10449, "caption": "man in middle"}, {"image_id": 10450, "caption": "woman in middle"}, {"image_id": 10412, "caption": "man on right"}, {"image_id": 10413, "caption": "left guy"}, {"image_id": 10374, "caption": "bear in"}, {"image_id": 10375, "caption": "bear in"}, {"image_id": 10376, "caption": "bear in"}, {"image_id": 10377, "caption": "bear in"}, {"image_id": 10332, "caption": "batter"}, {"image_id": 10271, "caption": "man in"}, {"image_id": 10272, "caption": "man in"}, {"image_id": 10217, "caption": "player in"}, {"image_id": 10218, "caption": "player in"}, {"image_id": 10219, "caption": "player in"}, {"image_id": 10136, "caption": "woman in blue"}, {"image_id": 10137, "caption": "woman in blue"}, {"image_id": 10138, "caption": "woman in blue"}, {"image_id": 10139, "caption": "woman in blue"}, {"image_id": 10140, "caption": "woman in blue"}, {"image_id": 10141, "caption": "woman in blue"}, {"image_id": 10114, "caption": "man in"}, {"image_id": 10115, "caption": "man in"}, {"image_id": 10047, "caption": "left on"}, {"image_id": 10048, "caption": "left on left"}, {"image_id": 10049, "caption": "left person"}, {"image_id": 10015, "caption": "man in"}, {"image_id": 10016, "caption": "guy in"}, {"image_id": 9949, "caption": "batter"}, {"image_id": 9950, "caption": "batter"}, {"image_id": 9865, "caption": "batter"}, {"image_id": 9866, "caption": "batter"}, {"image_id": 9867, "caption": "batter"}, {"image_id": 9856, "caption": "man in"}, {"image_id": 9857, "caption": "man in"}, {"image_id": 9858, "caption": "man in"}, {"image_id": 9799, "caption": "man in"}, {"image_id": 9800, "caption": "man in front"}, {"image_id": 9760, "caption": "player on right"}, {"image_id": 9761, "caption": "player on right"}, {"image_id": 9532, "caption": "man in"}, {"image_id": 9533, "caption": "man in"}, {"image_id": 9534, "caption": "man in"}, {"image_id": 9509, "caption": "woman in"}, {"image_id": 9510, "caption": "woman in"}, {"image_id": 9511, "caption": "woman in"}, {"image_id": 9493, "caption": "guy on left"}, {"image_id": 9494, "caption": "man on right"}, {"image_id": 9255, "caption": "woman in"}, {"image_id": 9256, "caption": "woman in"}, {"image_id": 9238, "caption": "person on left"}, {"image_id": 9239, "caption": "man in"}, {"image_id": 8896, "caption": "guy in"}, {"image_id": 8897, "caption": "man in"}, {"image_id": 8898, "caption": "man in"}, {"image_id": 8899, "caption": "man in"}, {"image_id": 8770, "caption": "man in blue"}, {"image_id": 8771, "caption": "woman in blue"}, {"image_id": 8772, "caption": "man in blue"}, {"image_id": 8773, "caption": "person in"}, {"image_id": 8774, "caption": "man in blue"}, {"image_id": 8758, "caption": "guy on right"}, {"image_id": 8759, "caption": "guy on"}, {"image_id": 8760, "caption": "man on right"}, {"image_id": 8699, "caption": "man in"}, {"image_id": 8700, "caption": "man in"}, {"image_id": 8701, "caption": "man in"}, {"image_id": 8694, "caption": "woman in"}, {"image_id": 8695, "caption": "woman in"}, {"image_id": 8696, "caption": "woman in"}, {"image_id": 8697, "caption": "woman in"}, {"image_id": 8698, "caption": "woman in"}, {"image_id": 8685, "caption": "man in"}, {"image_id": 8686, "caption": "man in"}, {"image_id": 8687, "caption": "guy in"}, {"image_id": 8500, "caption": "player in"}, {"image_id": 8501, "caption": "player in"}, {"image_id": 8502, "caption": "player in"}, {"image_id": 8490, "caption": "man in"}, {"image_id": 8491, "caption": "guy in front"}, {"image_id": 8492, "caption": "man in"}, {"image_id": 8413, "caption": "man in"}, {"image_id": 8414, "caption": "woman in"}, {"image_id": 8415, "caption": "man in"}, {"image_id": 8416, "caption": "man in"}, {"image_id": 8375, "caption": "bottom left"}, {"image_id": 8376, "caption": "man on right"}, {"image_id": 8377, "caption": "left cake"}, {"image_id": 8378, "caption": "man on left"}, {"image_id": 8379, "caption": "man"}, {"image_id": 8354, "caption": "person on left"}, {"image_id": 8355, "caption": "person in"}, {"image_id": 8356, "caption": "horse in"}, {"image_id": 8357, "caption": "left on left left left left left"}, {"image_id": 8308, "caption": "man in"}, {"image_id": 8309, "caption": "man in"}, {"image_id": 8310, "caption": "man on left"}, {"image_id": 8247, "caption": "woman in"}, {"image_id": 8248, "caption": "woman in"}, {"image_id": 8214, "caption": "man in"}, {"image_id": 8215, "caption": "man in"}, {"image_id": 8216, "caption": "man in"}, {"image_id": 8217, "caption": "man in"}, {"image_id": 8116, "caption": "man in"}, {"image_id": 8117, "caption": "man in"}, {"image_id": 8118, "caption": "player in"}, {"image_id": 8119, "caption": "player in"}, {"image_id": 8088, "caption": "guy on right"}, {"image_id": 8089, "caption": "man on right"}, {"image_id": 8086, "caption": "man on right"}, {"image_id": 8087, "caption": "man on"}, {"image_id": 8005, "caption": "batter"}, {"image_id": 8006, "caption": "batter"}, {"image_id": 7981, "caption": "man"}, {"image_id": 7982, "caption": "girl"}, {"image_id": 7967, "caption": "woman in"}, {"image_id": 7968, "caption": "woman in"}, {"image_id": 7969, "caption": "girl in"}, {"image_id": 7970, "caption": "girl in"}, {"image_id": 7929, "caption": "player in"}, {"image_id": 7930, "caption": "player in"}, {"image_id": 7890, "caption": "person in"}, {"image_id": 7891, "caption": "person in"}, {"image_id": 7854, "caption": "woman in"}, {"image_id": 7855, "caption": "guy in"}, {"image_id": 7856, "caption": "guy in"}, {"image_id": 7857, "caption": "man in"}, {"image_id": 7858, "caption": "guy in"}, {"image_id": 7851, "caption": "man on right"}, {"image_id": 7852, "caption": "man"}, {"image_id": 7853, "caption": "man in"}, {"image_id": 7742, "caption": "man in"}, {"image_id": 7743, "caption": "man in"}, {"image_id": 7710, "caption": "man in"}, {"image_id": 7711, "caption": "man in"}, {"image_id": 7712, "caption": "man in"}, {"image_id": 7612, "caption": "man on left"}, {"image_id": 7613, "caption": "man on right"}, {"image_id": 7608, "caption": "boy in middle"}, {"image_id": 7609, "caption": "boy in"}, {"image_id": 7610, "caption": "boy in"}, {"image_id": 7611, "caption": "boy in"}, {"image_id": 7571, "caption": "woman in"}, {"image_id": 7572, "caption": "girl in"}, {"image_id": 7573, "caption": "woman in"}, {"image_id": 7574, "caption": "woman in"}, {"image_id": 7575, "caption": "girl in"}, {"image_id": 7576, "caption": "woman in"}, {"image_id": 7568, "caption": "man in"}, {"image_id": 7569, "caption": "man in"}, {"image_id": 7570, "caption": "man in"}, {"image_id": 7496, "caption": "man in"}, {"image_id": 7497, "caption": "man in"}, {"image_id": 7498, "caption": "man in"}, {"image_id": 7499, "caption": "man in"}, {"image_id": 7477, "caption": "girl in"}, {"image_id": 7478, "caption": "man in blue"}, {"image_id": 7377, "caption": "man in"}, {"image_id": 7378, "caption": "man in"}, {"image_id": 7379, "caption": "man in"}, {"image_id": 7249, "caption": "batter"}, {"image_id": 7250, "caption": "batter"}, {"image_id": 7251, "caption": "batter"}, {"image_id": 7211, "caption": "black shirt"}, {"image_id": 7212, "caption": "black shirt"}, {"image_id": 7170, "caption": "batter"}, {"image_id": 7171, "caption": "batter"}, {"image_id": 7172, "caption": "batter"}, {"image_id": 7045, "caption": "woman in"}, {"image_id": 7046, "caption": "woman in"}, {"image_id": 7047, "caption": "girl on left"}, {"image_id": 6956, "caption": "player in"}, {"image_id": 6957, "caption": "player in"}, {"image_id": 6958, "caption": "man in"}, {"image_id": 6811, "caption": "batter"}, {"image_id": 6812, "caption": "batter"}, {"image_id": 6809, "caption": "man in"}, {"image_id": 6810, "caption": "man in"}, {"image_id": 6799, "caption": "player in"}, {"image_id": 6800, "caption": "man in"}, {"image_id": 6698, "caption": "player in"}, {"image_id": 6699, "caption": "player in"}, {"image_id": 6607, "caption": "top right"}, {"image_id": 6461, "caption": "woman"}, {"image_id": 6462, "caption": "woman"}, {"image_id": 6257, "caption": "man in"}, {"image_id": 6237, "caption": "kid in"}, {"image_id": 6238, "caption": "kid in"}, {"image_id": 6239, "caption": "kid in"}, {"image_id": 6210, "caption": "man on left"}, {"image_id": 6211, "caption": "man on right"}, {"image_id": 6118, "caption": "batter"}, {"image_id": 6119, "caption": "batter"}, {"image_id": 6081, "caption": "man on right"}, {"image_id": 6082, "caption": "man on right"}, {"image_id": 6073, "caption": "man in"}, {"image_id": 6074, "caption": "guy on left"}, {"image_id": 6042, "caption": "man on right"}, {"image_id": 6043, "caption": "man on right"}, {"image_id": 5923, "caption": "top right"}, {"image_id": 5924, "caption": "left on left left left left left left left left left"}, {"image_id": 5925, "caption": "bowl on left"}, {"image_id": 5926, "caption": "left on left left left left left left left"}, {"image_id": 5811, "caption": "woman in"}, {"image_id": 5812, "caption": "woman in"}, {"image_id": 5782, "caption": "man in"}, {"image_id": 5783, "caption": "man in"}, {"image_id": 5784, "caption": "man in"}, {"image_id": 5776, "caption": "left on"}, {"image_id": 5777, "caption": "left couch"}, {"image_id": 5767, "caption": "batter"}, {"image_id": 5768, "caption": "batter"}, {"image_id": 5769, "caption": "batter"}, {"image_id": 5648, "caption": "woman in"}, {"image_id": 5649, "caption": "woman in"}, {"image_id": 5650, "caption": "woman in"}, {"image_id": 5615, "caption": "man in"}, {"image_id": 5550, "caption": "man in"}, {"image_id": 5551, "caption": "man in"}, {"image_id": 5552, "caption": "man in"}, {"image_id": 5389, "caption": "person on right"}, {"image_id": 5390, "caption": "woman"}, {"image_id": 5309, "caption": "person in"}, {"image_id": 5310, "caption": "man in"}, {"image_id": 5311, "caption": "man in"}, {"image_id": 5289, "caption": "woman in"}, {"image_id": 5290, "caption": "woman in"}, {"image_id": 5291, "caption": "woman in"}, {"image_id": 5292, "caption": "woman in"}, {"image_id": 5293, "caption": "woman in"}, {"image_id": 5244, "caption": "guy on right"}, {"image_id": 5245, "caption": "guy on right"}, {"image_id": 5170, "caption": "left dog"}, {"image_id": 5171, "caption": "left dog"}, {"image_id": 5149, "caption": "girl in"}, {"image_id": 5150, "caption": "girl in"}, {"image_id": 5118, "caption": "guy in"}, {"image_id": 5119, "caption": "man in"}, {"image_id": 5012, "caption": "man in"}, {"image_id": 4868, "caption": "man in"}, {"image_id": 4869, "caption": "man in"}, {"image_id": 4870, "caption": "man in"}, {"image_id": 4765, "caption": "batter"}, {"image_id": 4766, "caption": "batter"}, {"image_id": 4711, "caption": "person on"}, {"image_id": 4712, "caption": "person on right"}, {"image_id": 4616, "caption": "man in"}, {"image_id": 4617, "caption": "man in"}, {"image_id": 4580, "caption": "man in black"}, {"image_id": 4581, "caption": "guy in front"}, {"image_id": 4582, "caption": "man in front"}, {"image_id": 4578, "caption": "woman in"}, {"image_id": 4579, "caption": "woman in"}, {"image_id": 4485, "caption": "horse on"}, {"image_id": 4486, "caption": "horse on right"}, {"image_id": 4487, "caption": "horse on right"}, {"image_id": 4488, "caption": "horse on right"}, {"image_id": 4489, "caption": "horse on right"}, {"image_id": 4461, "caption": "man on left"}, {"image_id": 4462, "caption": "man in"}, {"image_id": 4463, "caption": "man in"}, {"image_id": 4396, "caption": "woman in"}, {"image_id": 4397, "caption": "man in"}, {"image_id": 4345, "caption": "batter"}, {"image_id": 4346, "caption": "batter"}, {"image_id": 4347, "caption": "batter"}, {"image_id": 4333, "caption": "man on right"}, {"image_id": 4334, "caption": "man on right"}, {"image_id": 4308, "caption": "left on left"}, {"image_id": 4309, "caption": "left on left"}, {"image_id": 4191, "caption": "woman in"}, {"image_id": 4192, "caption": "woman in"}, {"image_id": 4190, "caption": "man on right"}, {"image_id": 4187, "caption": "boy in"}, {"image_id": 4188, "caption": "boy in"}, {"image_id": 4176, "caption": "girl in"}, {"image_id": 4177, "caption": "woman in"}, {"image_id": 4178, "caption": "woman in"}, {"image_id": 4174, "caption": "player on left"}, {"image_id": 4175, "caption": "player on left"}, {"image_id": 4159, "caption": "man in"}, {"image_id": 4160, "caption": "man in"}, {"image_id": 4143, "caption": "man in"}, {"image_id": 4144, "caption": "man in"}, {"image_id": 4145, "caption": "man in"}, {"image_id": 4101, "caption": "man on right"}, {"image_id": 4102, "caption": "guy on left"}, {"image_id": 4089, "caption": "woman in"}, {"image_id": 4090, "caption": "woman in"}, {"image_id": 4014, "caption": "woman in"}, {"image_id": 4015, "caption": "man in"}, {"image_id": 4016, "caption": "man in"}, {"image_id": 4017, "caption": "man in"}, {"image_id": 4002, "caption": "person on left"}, {"image_id": 4003, "caption": "person in front"}, {"image_id": 3805, "caption": "guy in"}, {"image_id": 3806, "caption": "man in"}, {"image_id": 3807, "caption": "guy in"}, {"image_id": 3772, "caption": "man on left"}, {"image_id": 3773, "caption": "man on right"}, {"image_id": 3768, "caption": "girl in"}, {"image_id": 3769, "caption": "girl in"}, {"image_id": 3366, "caption": "man in middle"}, {"image_id": 3367, "caption": "man in middle"}, {"image_id": 3257, "caption": "man in"}, {"image_id": 3258, "caption": "woman in"}, {"image_id": 3259, "caption": "woman in"}, {"image_id": 3260, "caption": "woman in"}, {"image_id": 3247, "caption": "left on"}, {"image_id": 3248, "caption": "left on"}, {"image_id": 2981, "caption": "woman in"}, {"image_id": 2982, "caption": "woman in"}, {"image_id": 2805, "caption": "batter"}, {"image_id": 2806, "caption": "batter"}, {"image_id": 2807, "caption": "catcher"}, {"image_id": 2767, "caption": "girl in"}, {"image_id": 2768, "caption": "girl in"}, {"image_id": 2721, "caption": "man on"}, {"image_id": 2722, "caption": "man on left"}, {"image_id": 2375, "caption": "man on right"}, {"image_id": 2376, "caption": "man on left"}, {"image_id": 2291, "caption": "man in"}, {"image_id": 2292, "caption": "man in"}, {"image_id": 2264, "caption": "man on left"}, {"image_id": 2265, "caption": "man on left"}, {"image_id": 2256, "caption": "batter"}, {"image_id": 2257, "caption": "batter"}, {"image_id": 2173, "caption": "man on right"}, {"image_id": 2174, "caption": "guy on right"}, {"image_id": 2129, "caption": "woman in"}, {"image_id": 2130, "caption": "woman in"}, {"image_id": 2131, "caption": "woman in"}, {"image_id": 2001, "caption": "player on right"}, {"image_id": 2002, "caption": "player on right"}, {"image_id": 1990, "caption": "left surfboard"}, {"image_id": 1991, "caption": "left on left left left left left left left"}, {"image_id": 1977, "caption": "man in"}, {"image_id": 1978, "caption": "man in"}, {"image_id": 1979, "caption": "man in"}, {"image_id": 1980, "caption": "man in"}, {"image_id": 1882, "caption": "woman"}, {"image_id": 1883, "caption": "woman"}, {"image_id": 1861, "caption": "guy in"}, {"image_id": 1862, "caption": "person in"}, {"image_id": 1811, "caption": "man in"}, {"image_id": 1812, "caption": "man in"}, {"image_id": 1679, "caption": "woman in middle"}, {"image_id": 1680, "caption": "woman in middle"}, {"image_id": 1681, "caption": "woman in middle"}, {"image_id": 1682, "caption": "woman in middle"}, {"image_id": 1683, "caption": "woman in middle"}, {"image_id": 1684, "caption": "woman in middle"}, {"image_id": 1623, "caption": "person in"}, {"image_id": 1624, "caption": "person in"}, {"image_id": 1582, "caption": "man in blue"}, {"image_id": 1583, "caption": "man in blue"}, {"image_id": 1568, "caption": "guy on left"}, {"image_id": 1569, "caption": "guy on right"}, {"image_id": 1406, "caption": "man in"}, {"image_id": 1407, "caption": "man in"}, {"image_id": 1371, "caption": "woman"}, {"image_id": 1372, "caption": "woman"}, {"image_id": 1362, "caption": "man on right"}, {"image_id": 1363, "caption": "man on"}, {"image_id": 1333, "caption": "woman in"}, {"image_id": 1334, "caption": "man in"}, {"image_id": 1152, "caption": "woman in"}, {"image_id": 1153, "caption": "woman in"}, {"image_id": 1154, "caption": "woman in"}, {"image_id": 1052, "caption": "man on left"}, {"image_id": 1053, "caption": "man in"}, {"image_id": 1023, "caption": "left on left"}, {"image_id": 1024, "caption": "left on left left left"}, {"image_id": 954, "caption": "man in"}, {"image_id": 955, "caption": "man in"}, {"image_id": 956, "caption": "man in"}, {"image_id": 945, "caption": "man in"}, {"image_id": 946, "caption": "man in"}, {"image_id": 947, "caption": "man in"}, {"image_id": 931, "caption": "woman in"}, {"image_id": 932, "caption": "woman in"}, {"image_id": 933, "caption": "woman in"}, {"image_id": 828, "caption": "woman in"}, {"image_id": 829, "caption": "woman in"}, {"image_id": 814, "caption": "man in"}, {"image_id": 815, "caption": "man in"}, {"image_id": 756, "caption": "man in"}, {"image_id": 757, "caption": "person in"}, {"image_id": 732, "caption": "man on left"}, {"image_id": 733, "caption": "man on right"}, {"image_id": 734, "caption": "man on right"}, {"image_id": 640, "caption": "woman in"}, {"image_id": 641, "caption": "woman in"}, {"image_id": 588, "caption": "kid in"}, {"image_id": 589, "caption": "boy in blue"}, {"image_id": 557, "caption": "man in"}, {"image_id": 558, "caption": "man in"}, {"image_id": 537, "caption": "player in"}, {"image_id": 538, "caption": "player in"}, {"image_id": 539, "caption": "player in"}, {"image_id": 525, "caption": "man in"}, {"image_id": 526, "caption": "man in"}, {"image_id": 527, "caption": "man in"}, {"image_id": 528, "caption": "man in"}, {"image_id": 519, "caption": "man in"}, {"image_id": 520, "caption": "man in"}, {"image_id": 382, "caption": "left on left left left"}, {"image_id": 383, "caption": "left guy"}, {"image_id": 109, "caption": "man on right"}, {"image_id": 110, "caption": "man on right"}, {"image_id": 111, "caption": "left truck"}, {"image_id": 112, "caption": "man in"}, {"image_id": 47, "caption": "man in"}]